[
  {
    "action": "updated",
    "id": 7676898967636,
    "title": "Dummy Title"
  },
  {
    "action": "updated",
    "id": 7676899459156,
    "title": "Dummy Title 2"
  },
  {
    "action": "updated",
    "id": 7670809002068,
    "title": "Gift Card"
  },
  {
    "action": "updated",
    "id": 7677205708884,
    "title": "hakuna matata"
  },
  {
    "action": "updated",
    "id": 7677136863316,
    "title": "N"
  },
  {
    "action": "updated",
    "id": 7677207117908,
    "title": "new item1"
  },
  {
    "action": "updated",
    "id": 7691935711316,
    "title": "New product"
  },
  {
    "action": "updated",
    "id": 7677104947284,
    "title": "nocturno"
  },
  {
    "action": "updated",
    "id": 7677107404884,
    "title": "Pommes"
  },
  {
    "action": "updated",
    "id": 7691957076052,
    "title": "Product title"
  },
  {
    "action": "updated",
    "id": 7659537858644,
    "title": "Selling Plans Ski Wax"
  },
  {
    "action": "updated",
    "id": 7670848815188,
    "title": "Test Product A"
  },
  {
    "action": "updated",
    "id": 7497324036180,
    "title": "The 3p Fulfilled Snowboard"
  },
  {
    "action": "updated",
    "id": 7497324068948,
    "title": "The Archived Snowboard"
  },
  {
    "action": "updated",
    "id": 7497324101716,
    "title": "The Collection Snowboard: Hydrogen"
  },
  {
    "action": "updated",
    "id": 7497324134484,
    "title": "The Collection Snowboard: Liquid"
  },
  {
    "action": "updated",
    "id": 7497324200020,
    "title": "The Collection Snowboard: Oxygen"
  },
  {
    "action": "updated",
    "id": 7497324232788,
    "title": "The Compare at Price Snowboard"
  },
  {
    "action": "updated",
    "id": 7497324298324,
    "title": "The Complete Snowboard"
  },
  {
    "action": "updated",
    "id": 7497324331092,
    "title": "The Draft Snowboard"
  },
  {
    "action": "updated",
    "id": 7497324363860,
    "title": "The Hidden Snowboard"
  },
  {
    "action": "updated",
    "id": 7497324396628,
    "title": "The Inventory Not Tracked Snowboard"
  },
  {
    "action": "updated",
    "id": 7497324429396,
    "title": "The Minimal Snowboard"
  },
  {
    "action": "updated",
    "id": 7497324494932,
    "title": "The Multi-location Snowboard"
  },
  {
    "action": "updated",
    "id": 7497324527700,
    "title": "The Multi-managed Snowboard"
  },
  {
    "action": "updated",
    "id": 7497324593236,
    "title": "The Out of Stock Snowboard"
  },
  {
    "action": "updated",
    "id": 7497324658772,
    "title": "The Videographer Snowboard"
  },
  {
    "action": "updated",
    "id": 7677104980052,
    "title": "Uno Due Tre"
  },
  {
    "action": "updated",
    "id": 7677105012820,
    "title": "Uno Due Tre"
  },
  {
    "action": "updated",
    "id": 7677135978580,
    "title": "Z"
  }
]